{"Team": [{"team_name": "Atlanta Hawks", "team_id": 1}, {"team_name": "Baltimore/Capital/Washington Bullets", "team_id": 2}, {"team_name": "Boston Celtics", "team_id": 3}, {"team_name": "Brooklyn Nets", "team_id": 4}, {"team_name": "Buffalo Braves", "team_id": 5}, {"team_name": "Charlotte Hornets", "team_id": 6}, {"team_name": "Chicago Bulls", "team_id": 7}, {"team_name": "Chicago Packers/Zephyrs/Baltimore Bullets", "team_id": 8}, {"team_name": "Cincinnati Royals", "team_id": 9}, {"team_name": "Cleveland Cavaliers", "team_id": 10}, {"team_name": "Dallas Mavericks", "team_id": 11}, {"team_name": "Denver Nuggets", "team_id": 12}, {"team_name": "Detroit Pistons", "team_id": 13}, {"team_name": "Golden State Warriors", "team_id": 14}, {"team_name": "Houston Rockets", "team_id": 15}, {"team_name": "Indiana Pacers", "team_id": 16}, {"team_name": "Los Angeles Clippers", "team_id": 17}, {"team_name": "Los Angeles Lakers", "team_id": 18}, {"team_name": "Memphis Grizzlies", "team_id": 19}, {"team_name": "Miami Heat", "team_id": 20}, {"team_name": "Milwaukee Bucks", "team_id": 21}, {"team_name": "Milwaukee/St. Louis Hawks", "team_id": 22}, {"team_name": "Minneapolis/Los Angeles Lakers", "team_id": 23}, {"team_name": "Minnesota Timberwolves", "team_id": 24}, {"team_name": "New Jersey Nets", "team_id": 25}, {"team_name": "New Orleans Hornets", "team_id": 26}, {"team_name": "New Orleans Jazz", "team_id": 27}, {"team_name": "New York Knicks", "team_id": 28}, {"team_name": "Oklahoma City Thunder", "team_id": 29}, {"team_name": "Orlando Magic", "team_id": 30}, {"team_name": "Philadelphia 76ers", "team_id": 31}, {"team_name": "Philadelphia/San Francisco Warriors", "team_id": 32}, {"team_name": "Phoenix Suns", "team_id": 33}, {"team_name": "Portland Trail Blazers", "team_id": 34}, {"team_name": "Sacramento Kings", "team_id": 35}, {"team_name": "San Antonio Spurs", "team_id": 36}, {"team_name": "San Diego Clippers", "team_id": 37}, {"team_name": "San Diego/Houston Rockets", "team_id": 38}, {"team_name": "Seattle SuperSonics", "team_id": 39}, {"team_name": "Seattle SuperSonics/Oklahoma City Thunder", "team_id": 40}, {"team_name": "Syracuse Nationals/Philadelphia 76ers", "team_id": 41}, {"team_name": "Toronto Raptors", "team_id": 42}, {"team_name": "Utah Jazz", "team_id": 43}, {"team_name": "Washington Bullets", "team_id": 44}, {"team_name": "Washington Wizards", "team_id": 45}], "Player": [{"player_id": 1, "player_name": "LeBron James", "pos": "SF"}, {"player_id": 2, "player_name": "Kareem Abdul-Jabbar", "pos": "C"}, {"player_id": 3, "player_name": "Karl Malone", "pos": "PF"}, {"player_id": 4, "player_name": "Kobe Bryant", "pos": "SG"}, {"player_id": 5, "player_name": "Michael Jordan", "pos": "SG"}, {"player_id": 6, "player_name": "Dirk Nowitzki", "pos": "PF/C"}, {"player_id": 7, "player_name": "Wilt Chamberlain", "pos": "C"}, {"player_id": 8, "player_name": "Shaquille O'Neal", "pos": "C"}, {"player_id": 9, "player_name": "Carmelo Anthony", "pos": "SF"}, {"player_id": 10, "player_name": "Kevin Durant", "pos": "SF/PF"}, {"player_id": 11, "player_name": "Moses Malone", "pos": "C"}, {"player_id": 12, "player_name": "Elvin Hayes", "pos": "PF/C"}, {"player_id": 13, "player_name": "Hakeem Olajuwon", "pos": "C"}, {"player_id": 14, "player_name": "Oscar Robertson", "pos": "PG"}, {"player_id": 15, "player_name": "Dominique Wilkins", "pos": "SF"}, {"player_id": 16, "player_name": "Tim Duncan", "pos": "PF/C"}, {"player_id": 17, "player_name": "Paul Pierce", "pos": "SF/SG"}, {"player_id": 18, "player_name": "John Havlicek", "pos": "SF/SG"}, {"player_id": 19, "player_name": "Kevin Garnett", "pos": "PF/C"}, {"player_id": 20, "player_name": "Vince Carter", "pos": "SG/SF"}, {"player_id": 21, "player_name": "Alex English", "pos": "SF"}, {"player_id": 22, "player_name": "Reggie Miller", "pos": "SG"}, {"player_id": 23, "player_name": "Jerry West", "pos": "PG/SG"}, {"player_id": 24, "player_name": "James Harden", "pos": "SG/PG"}, {"player_id": 25, "player_name": "Patrick Ewing", "pos": "C"}, {"player_id": 26, "player_name": "Russell Westbrook", "pos": "PG"}, {"player_id": 27, "player_name": "Ray Allen", "pos": "SG"}, {"player_id": 28, "player_name": "Allen Iverson", "pos": "SG/PG"}, {"player_id": 29, "player_name": "Charles Barkley", "pos": "PF"}, {"player_id": 30, "player_name": "Robert Parish", "pos": "C"}, {"player_id": 31, "player_name": "Adrian Dantley", "pos": "SF"}, {"player_id": 32, "player_name": "Dwyane Wade", "pos": "SG"}, {"player_id": 33, "player_name": "Elgin Baylor", "pos": "SF"}, {"player_id": 34, "player_name": "Stephen Curry", "pos": "PG"}, {"player_id": 35, "player_name": "Clyde Drexler", "pos": "SG"}, {"player_id": 36, "player_name": "DeMar DeRozan", "pos": "SG/SF"}, {"player_id": 37, "player_name": "Chris Paul", "pos": "PG"}, {"player_id": 38, "player_name": "Gary Payton", "pos": "PG"}, {"player_id": 39, "player_name": "Larry Bird", "pos": "SF/PF"}, {"player_id": 40, "player_name": "Hal Greer", "pos": "SG/PG"}, {"player_id": 41, "player_name": "Walt Bellamy", "pos": "C"}, {"player_id": 42, "player_name": "Pau Gasol", "pos": "C/PF"}, {"player_id": 43, "player_name": "Bob Pettit", "pos": "PF/C"}, {"player_id": 44, "player_name": "David Robinson", "pos": "C"}, {"player_id": 45, "player_name": "George Gervin", "pos": "SG/SF"}, {"player_id": 46, "player_name": "LaMarcus Aldridge", "pos": "PF/C"}, {"player_id": 47, "player_name": "Mitch Richmond", "pos": "SG"}, {"player_id": 48, "player_name": "Joe Johnson", "pos": "SG/SF"}, {"player_id": 49, "player_name": "Tom Chambers", "pos": "PF"}, {"player_id": 50, "player_name": "Antawn Jamison", "pos": "PF/SF"}], "PlayerStats": [{"rank_id": 1, "player_id": 1, "total_points": 39201, "total_games": 1443, "points_per_game": 27, "three_points_goals": 2311, "free_shots": 8178, "field_goals": 14356}, {"rank_id": 2, "player_id": 2, "total_points": 38387, "total_games": 1560, "points_per_game": 25, "three_points_goals": 1, "free_shots": 6712, "field_goals": 15837}, {"rank_id": 3, "player_id": 3, "total_points": 36928, "total_games": 1476, "points_per_game": 25, "three_points_goals": 85, "free_shots": 9787, "field_goals": 13528}, {"rank_id": 4, "player_id": 4, "total_points": 33643, "total_games": 1346, "points_per_game": 25, "three_points_goals": 1827, "free_shots": 8378, "field_goals": 11719}, {"rank_id": 5, "player_id": 5, "total_points": 32292, "total_games": 1072, "points_per_game": 30, "three_points_goals": 581, "free_shots": 7327, "field_goals": 12192}, {"rank_id": 6, "player_id": 6, "total_points": 31560, "total_games": 1522, "points_per_game": 21, "three_points_goals": 1982, "free_shots": 7240, "field_goals": 11169}, {"rank_id": 7, "player_id": 7, "total_points": 31419, "total_games": 1045, "points_per_game": 30, "three_points_goals": 0, "free_shots": 6057, "field_goals": 12681}, {"rank_id": 8, "player_id": 8, "total_points": 28596, "total_games": 1207, "points_per_game": 24, "three_points_goals": 1, "free_shots": 5935, "field_goals": 11330}, {"rank_id": 9, "player_id": 9, "total_points": 28289, "total_games": 1260, "points_per_game": 23, "three_points_goals": 1731, "free_shots": 6320, "field_goals": 10119}, {"rank_id": 10, "player_id": 10, "total_points": 27481, "total_games": 1005, "points_per_game": 27, "three_points_goals": 1907, "free_shots": 6772, "field_goals": 9401}, {"rank_id": 11, "player_id": 11, "total_points": 27409, "total_games": 1329, "points_per_game": 21, "three_points_goals": 8, "free_shots": 8531, "field_goals": 9435}, {"rank_id": 12, "player_id": 12, "total_points": 27313, "total_games": 1303, "points_per_game": 21, "three_points_goals": 5, "free_shots": 5356, "field_goals": 10976}, {"rank_id": 13, "player_id": 13, "total_points": 26946, "total_games": 1238, "points_per_game": 22, "three_points_goals": 25, "free_shots": 5423, "field_goals": 10749}, {"rank_id": 14, "player_id": 14, "total_points": 26710, "total_games": 1040, "points_per_game": 26, "three_points_goals": 0, "free_shots": 7694, "field_goals": 9508}, {"rank_id": 15, "player_id": 15, "total_points": 26668, "total_games": 1074, "points_per_game": 25, "three_points_goals": 711, "free_shots": 6031, "field_goals": 9963}, {"rank_id": 16, "player_id": 16, "total_points": 26496, "total_games": 1392, "points_per_game": 19, "three_points_goals": 30, "free_shots": 5896, "field_goals": 10285}, {"rank_id": 17, "player_id": 17, "total_points": 26397, "total_games": 1343, "points_per_game": 20, "three_points_goals": 2143, "free_shots": 6918, "field_goals": 8668}, {"rank_id": 18, "player_id": 18, "total_points": 26395, "total_games": 1270, "points_per_game": 21, "three_points_goals": 0, "free_shots": 5369, "field_goals": 10513}, {"rank_id": 19, "player_id": 19, "total_points": 26071, "total_games": 1462, "points_per_game": 18, "three_points_goals": 174, "free_shots": 4887, "field_goals": 10505}, {"rank_id": 20, "player_id": 20, "total_points": 25728, "total_games": 1541, "points_per_game": 17, "three_points_goals": 2290, "free_shots": 4852, "field_goals": 9293}, {"rank_id": 21, "player_id": 21, "total_points": 25613, "total_games": 1193, "points_per_game": 22, "three_points_goals": 18, "free_shots": 4277, "field_goals": 10659}, {"rank_id": 22, "player_id": 22, "total_points": 25279, "total_games": 1389, "points_per_game": 18, "three_points_goals": 2560, "free_shots": 6237, "field_goals": 8241}, {"rank_id": 23, "player_id": 23, "total_points": 25192, "total_games": 932, "points_per_game": 27, "three_points_goals": 0, "free_shots": 7160, "field_goals": 9016}, {"rank_id": 24, "player_id": 24, "total_points": 24945, "total_games": 1016, "points_per_game": 25, "three_points_goals": 2792, "free_shots": 7421, "field_goals": 7366}, {"rank_id": 25, "player_id": 25, "total_points": 24815, "total_games": 1183, "points_per_game": 21, "three_points_goals": 19, "free_shots": 5392, "field_goals": 9702}, {"rank_id": 26, "player_id": 26, "total_points": 24699, "total_games": 1115, "points_per_game": 22, "three_points_goals": 1246, "free_shots": 5753, "field_goals": 8850}, {"rank_id": 27, "player_id": 27, "total_points": 24505, "total_games": 1300, "points_per_game": 19, "three_points_goals": 2973, "free_shots": 4398, "field_goals": 8567}, {"rank_id": 28, "player_id": 28, "total_points": 24368, "total_games": 914, "points_per_game": 27, "three_points_goals": 1059, "free_shots": 6375, "field_goals": 8467}, {"rank_id": 29, "player_id": 29, "total_points": 23757, "total_games": 1073, "points_per_game": 22, "three_points_goals": 538, "free_shots": 6349, "field_goals": 8435}, {"rank_id": 30, "player_id": 30, "total_points": 23334, "total_games": 1611, "points_per_game": 15, "three_points_goals": 0, "free_shots": 4106, "field_goals": 9614}, {"rank_id": 31, "player_id": 31, "total_points": 23177, "total_games": 955, "points_per_game": 24, "three_points_goals": 7, "free_shots": 6832, "field_goals": 8169}, {"rank_id": 32, "player_id": 32, "total_points": 23165, "total_games": 1054, "points_per_game": 22, "three_points_goals": 549, "free_shots": 5708, "field_goals": 8454}, {"rank_id": 33, "player_id": 33, "total_points": 23149, "total_games": 846, "points_per_game": 27, "three_points_goals": 0, "free_shots": 5763, "field_goals": 8693}, {"rank_id": 34, "player_id": 34, "total_points": 22300, "total_games": 902, "points_per_game": 25, "three_points_goals": 3492, "free_shots": 3582, "field_goals": 7613}, {"rank_id": 35, "player_id": 35, "total_points": 22195, "total_games": 1086, "points_per_game": 20, "three_points_goals": 827, "free_shots": 4698, "field_goals": 8335}, {"rank_id": 36, "player_id": 36, "total_points": 22142, "total_games": 1052, "points_per_game": 21, "three_points_goals": 475, "free_shots": 5767, "field_goals": 7950}, {"rank_id": 37, "player_id": 37, "total_points": 21918, "total_games": 1233, "points_per_game": 18, "three_points_goals": 1663, "free_shots": 4755, "field_goals": 7750}, {"rank_id": 38, "player_id": 38, "total_points": 21813, "total_games": 1335, "points_per_game": 16, "three_points_goals": 1132, "free_shots": 3265, "field_goals": 8708}, {"rank_id": 39, "player_id": 39, "total_points": 21791, "total_games": 897, "points_per_game": 24, "three_points_goals": 649, "free_shots": 3960, "field_goals": 8591}, {"rank_id": 40, "player_id": 40, "total_points": 21586, "total_games": 1122, "points_per_game": 19, "three_points_goals": 0, "free_shots": 4578, "field_goals": 8504}, {"rank_id": 41, "player_id": 41, "total_points": 20941, "total_games": 1043, "points_per_game": 20, "three_points_goals": 0, "free_shots": 5113, "field_goals": 7914}, {"rank_id": 42, "player_id": 42, "total_points": 20894, "total_games": 1226, "points_per_game": 17, "three_points_goals": 179, "free_shots": 4755, "field_goals": 7980}, {"rank_id": 43, "player_id": 43, "total_points": 20880, "total_games": 792, "points_per_game": 26, "three_points_goals": 0, "free_shots": 6182, "field_goals": 7349}, {"rank_id": 44, "player_id": 44, "total_points": 20790, "total_games": 987, "points_per_game": 21, "three_points_goals": 25, "free_shots": 6035, "field_goals": 7365}, {"rank_id": 45, "player_id": 45, "total_points": 20708, "total_games": 791, "points_per_game": 26, "three_points_goals": 77, "free_shots": 4541, "field_goals": 8045}, {"rank_id": 46, "player_id": 46, "total_points": 20558, "total_games": 1076, "points_per_game": 19, "three_points_goals": 227, "free_shots": 3709, "field_goals": 8311}, {"rank_id": 47, "player_id": 47, "total_points": 20497, "total_games": 976, "points_per_game": 21, "three_points_goals": 1326, "free_shots": 4561, "field_goals": 7305}, {"rank_id": 48, "player_id": 48, "total_points": 20407, "total_games": 1277, "points_per_game": 16, "three_points_goals": 1978, "free_shots": 2783, "field_goals": 7823}, {"rank_id": 49, "player_id": 49, "total_points": 20049, "total_games": 1107, "points_per_game": 18, "three_points_goals": 227, "free_shots": 5066, "field_goals": 7378}, {"rank_id": 50, "player_id": 50, "total_points": 20042, "total_games": 1083, "points_per_game": 19, "three_points_goals": 1163, "free_shots": 3521, "field_goals": 7679}], "PlayersInTeams": [{"player_id": 1, "team_id": 10}, {"player_id": 1, "team_id": 20}, {"player_id": 1, "team_id": 18}, {"player_id": 2, "team_id": 21}, {"player_id": 2, "team_id": 18}, {"player_id": 3, "team_id": 43}, {"player_id": 3, "team_id": 18}, {"player_id": 4, "team_id": 18}, {"player_id": 5, "team_id": 7}, {"player_id": 5, "team_id": 45}, {"player_id": 6, "team_id": 11}, {"player_id": 7, "team_id": 32}, {"player_id": 7, "team_id": 31}, {"player_id": 7, "team_id": 18}, {"player_id": 8, "team_id": 30}, {"player_id": 8, "team_id": 18}, {"player_id": 8, "team_id": 20}, {"player_id": 8, "team_id": 33}, {"player_id": 8, "team_id": 10}, {"player_id": 8, "team_id": 3}, {"player_id": 9, "team_id": 12}, {"player_id": 9, "team_id": 28}, {"player_id": 9, "team_id": 29}, {"player_id": 9, "team_id": 15}, {"player_id": 9, "team_id": 34}, {"player_id": 9, "team_id": 18}, {"player_id": 10, "team_id": 40}, {"player_id": 10, "team_id": 14}, {"player_id": 10, "team_id": 4}, {"player_id": 10, "team_id": 33}, {"player_id": 11, "team_id": 5}, {"player_id": 11, "team_id": 15}, {"player_id": 11, "team_id": 31}, {"player_id": 11, "team_id": 44}, {"player_id": 11, "team_id": 1}, {"player_id": 11, "team_id": 21}, {"player_id": 11, "team_id": 36}, {"player_id": 12, "team_id": 38}, {"player_id": 12, "team_id": 2}, {"player_id": 13, "team_id": 15}, {"player_id": 13, "team_id": 42}, {"player_id": 14, "team_id": 9}, {"player_id": 14, "team_id": 21}, {"player_id": 15, "team_id": 1}, {"player_id": 15, "team_id": 17}, {"player_id": 15, "team_id": 3}, {"player_id": 15, "team_id": 36}, {"player_id": 15, "team_id": 30}, {"player_id": 16, "team_id": 36}, {"player_id": 17, "team_id": 3}, {"player_id": 17, "team_id": 4}, {"player_id": 17, "team_id": 45}, {"player_id": 17, "team_id": 17}, {"player_id": 18, "team_id": 3}, {"player_id": 19, "team_id": 24}, {"player_id": 19, "team_id": 3}, {"player_id": 19, "team_id": 4}, {"player_id": 20, "team_id": 42}, {"player_id": 20, "team_id": 25}, {"player_id": 20, "team_id": 30}, {"player_id": 20, "team_id": 33}, {"player_id": 20, "team_id": 11}, {"player_id": 20, "team_id": 19}, {"player_id": 20, "team_id": 35}, {"player_id": 20, "team_id": 1}, {"player_id": 21, "team_id": 21}, {"player_id": 21, "team_id": 16}, {"player_id": 21, "team_id": 12}, {"player_id": 21, "team_id": 11}, {"player_id": 22, "team_id": 16}, {"player_id": 23, "team_id": 18}, {"player_id": 24, "team_id": 29}, {"player_id": 24, "team_id": 15}, {"player_id": 24, "team_id": 4}, {"player_id": 24, "team_id": 31}, {"player_id": 24, "team_id": 17}, {"player_id": 25, "team_id": 28}, {"player_id": 25, "team_id": 39}, {"player_id": 25, "team_id": 30}, {"player_id": 26, "team_id": 29}, {"player_id": 26, "team_id": 15}, {"player_id": 26, "team_id": 45}, {"player_id": 26, "team_id": 18}, {"player_id": 26, "team_id": 17}, {"player_id": 27, "team_id": 21}, {"player_id": 27, "team_id": 39}, {"player_id": 27, "team_id": 3}, {"player_id": 27, "team_id": 20}, {"player_id": 28, "team_id": 31}, {"player_id": 28, "team_id": 12}, {"player_id": 28, "team_id": 13}, {"player_id": 28, "team_id": 19}, {"player_id": 29, "team_id": 31}, {"player_id": 29, "team_id": 33}, {"player_id": 29, "team_id": 15}, {"player_id": 30, "team_id": 14}, {"player_id": 30, "team_id": 3}, {"player_id": 30, "team_id": 6}, {"player_id": 30, "team_id": 7}, {"player_id": 31, "team_id": 5}, {"player_id": 31, "team_id": 16}, {"player_id": 31, "team_id": 18}, {"player_id": 31, "team_id": 43}, {"player_id": 31, "team_id": 13}, {"player_id": 31, "team_id": 11}, {"player_id": 31, "team_id": 21}, {"player_id": 32, "team_id": 20}, {"player_id": 32, "team_id": 7}, {"player_id": 32, "team_id": 10}, {"player_id": 33, "team_id": 23}, {"player_id": 34, "team_id": 14}, {"player_id": 35, "team_id": 34}, {"player_id": 35, "team_id": 15}, {"player_id": 36, "team_id": 42}, {"player_id": 36, "team_id": 36}, {"player_id": 36, "team_id": 7}, {"player_id": 37, "team_id": 26}, {"player_id": 37, "team_id": 17}, {"player_id": 37, "team_id": 15}, {"player_id": 37, "team_id": 29}, {"player_id": 37, "team_id": 33}, {"player_id": 37, "team_id": 14}, {"player_id": 38, "team_id": 39}, {"player_id": 38, "team_id": 21}, {"player_id": 38, "team_id": 18}, {"player_id": 38, "team_id": 3}, {"player_id": 38, "team_id": 20}, {"player_id": 39, "team_id": 3}, {"player_id": 40, "team_id": 41}, {"player_id": 41, "team_id": 8}, {"player_id": 41, "team_id": 28}, {"player_id": 41, "team_id": 13}, {"player_id": 41, "team_id": 1}, {"player_id": 41, "team_id": 27}, {"player_id": 42, "team_id": 19}, {"player_id": 42, "team_id": 18}, {"player_id": 42, "team_id": 7}, {"player_id": 42, "team_id": 36}, {"player_id": 42, "team_id": 21}, {"player_id": 43, "team_id": 22}, {"player_id": 44, "team_id": 36}, {"player_id": 45, "team_id": 36}, {"player_id": 45, "team_id": 7}, {"player_id": 46, "team_id": 34}, {"player_id": 46, "team_id": 36}, {"player_id": 46, "team_id": 4}, {"player_id": 47, "team_id": 14}, {"player_id": 47, "team_id": 35}, {"player_id": 47, "team_id": 45}, {"player_id": 47, "team_id": 18}, {"player_id": 48, "team_id": 3}, {"player_id": 48, "team_id": 33}, {"player_id": 48, "team_id": 1}, {"player_id": 48, "team_id": 4}, {"player_id": 48, "team_id": 20}, {"player_id": 48, "team_id": 43}, {"player_id": 48, "team_id": 15}, {"player_id": 49, "team_id": 37}, {"player_id": 49, "team_id": 39}, {"player_id": 49, "team_id": 33}, {"player_id": 49, "team_id": 43}, {"player_id": 49, "team_id": 6}, {"player_id": 49, "team_id": 31}, {"player_id": 50, "team_id": 14}, {"player_id": 50, "team_id": 11}, {"player_id": 50, "team_id": 45}, {"player_id": 50, "team_id": 10}, {"player_id": 50, "team_id": 18}, {"player_id": 50, "team_id": 17}]}